zt_privacy_lib/__init__.py
zt_privacy_lib/__main__.py
zt_privacy_lib/main.py
zt_privacy_lib/schema/pii_prompt.py
zt_privacy_lib/tools/__init__.py
zt_privacy_lib/tools/api_key_hashing.py
zt_privacy_lib/tools/pii_detection/__init__.py
zt_privacy_lib/tools/pii_detection/detect_pii.py
zt_privacy_lib/tools/pii_detection/schema/__init__.py
zt_privacy_lib/tools/pii_detection/schema/detect_anonymize_pii.py
zt_privacy_lib/tools/pii_detection/schema/pii_prompt.py
zt_privacy_lib/tools/pii_detection/services/__init__.py
zt_privacy_lib/tools/pii_detection/services/detect_anonymize_pii_service.py
zt_privacy_lib/tools/pii_detection/services/detect_anonymize_pii_service_strict.py
zt_privacy_lib/tools/pii_detection/services/detect_pii_gliner.py
zt_privacy_lib/tools/pii_detection/utils/__init__.py
zt_privacy_lib/tools/pii_detection/utils/constants.py
zt_privacy_lib-0.1.6.dist-info/entry_points.txt
zt_privacy_lib-0.1.6.dist-info/METADATA
zt_privacy_lib-0.1.6.dist-info/WHEEL
zt_privacy_lib-0.1.6.dist-info/RECORD
